README.md
setup.py
CantrelleJouisseMamannTest2.egg-info/PKG-INFO
CantrelleJouisseMamannTest2.egg-info/SOURCES.txt
CantrelleJouisseMamannTest2.egg-info/dependency_links.txt
CantrelleJouisseMamannTest2.egg-info/top_level.txt
philcantrel/Data_viz_a_packager_propre.py
philcantrel/__init__.py
philcantrel/module_carte.py