Metadata-Version: 2.1
Name: CantrelleJouisseMamannTest2
Version: 0.0.1
Summary: Package dataviz 2A ensae Philippe Cantrelle
Home-page: UNKNOWN
Author: Philippe Cantrelle
Author-email: philippe.cantrelle@ensae.fr
License: UNKNOWN
Platform: UNKNOWN
Classifier: Programming Language :: Python :: 3
Classifier: License :: OSI Approved :: MIT License
Classifier: Operating System :: OS Independent
Requires-Python: >=3.6
